sparkmon/__init__.py
sparkmon/__main__.py
sparkmon/application.py
sparkmon/callbacks.py
sparkmon/logger.py
sparkmon/mlflow_utils.py
sparkmon/monitor.py
sparkmon/plotting.py
sparkmon/py.typed
sparkmon/utils.py
sparkmon-0.1.10.dist-info/entry_points.txt
sparkmon-0.1.10.dist-info/LICENSE.rst
sparkmon-0.1.10.dist-info/WHEEL
sparkmon-0.1.10.dist-info/METADATA
sparkmon-0.1.10.dist-info/RECORD
