Metadata-Version: 2.1
Name: sparkmon
Version: 0.1.10
Summary: sparkmon
Home-page: https://github.com/stephanecollot/sparkmon
License: MIT
Author: Stephane Collot
Author-email: stephane.collot@ing.com
Requires-Python: >=3.6.1,<4.0.0
Classifier: License :: OSI Approved :: MIT License
Classifier: Programming Language :: Python :: 3
Classifier: Programming Language :: Python :: 3.10
Classifier: Programming Language :: Python :: 3.6
Classifier: Programming Language :: Python :: 3.7
Classifier: Programming Language :: Python :: 3.8
Classifier: Programming Language :: Python :: 3.9
Provides-Extra: mlflow
Requires-Dist: click
Requires-Dist: data-science-types
Requires-Dist: ipython
Requires-Dist: matplotlib
Requires-Dist: mlflow; extra == "mlflow"
Requires-Dist: pandas
Requires-Dist: pandas-stubs
Requires-Dist: psutil
Requires-Dist: pyspark
Requires-Dist: urlpath
Project-URL: Changelog, https://github.com/stephanecollot/sparkmon/releases
Project-URL: Documentation, https://sparkmon.readthedocs.io
Project-URL: Repository, https://github.com/stephanecollot/sparkmon
